adder.t.v
// Adder testbench
`timescale 1 ns / 1 ps
`include "adder.v"

module testFullAdder();

    reg a, b, carryin;
    wire sum, carryout;

    structuralFullAdder adder(sum, carryout, a, b, carryin);

    initial begin
	$dumpfile("<adder>.vcd");
	$dumpvars();
        $display("A | B | Cin | Cout | Sum|Exp Sum|Exp Out ");
	a = 0; b = 0; carryin = 0; #50
	$display("%b | %b | %b   | %b    | %b  |  0    |   0", a, b, carryin, carryout, sum);
	a = 0; b = 0; carryin = 1; #50
	$display("%b | %b | %b   | %b    | %b  |  1    |   0", a, b, carryin, carryout, sum);
	a = 0; b = 1; carryin = 0; #50
	$display("%b | %b | %b   | %b    | %b  |  1    |   0", a, b, carryin, carryout, sum);
	a = 0; b = 1; carryin = 1; #50
	$display("%b | %b | %b   | %b    | %b  |  0    |   1", a, b, carryin, carryout, sum);
	a = 1; b = 0; carryin = 0; #50
	$display("%b | %b | %b   | %b    | %b  |  1    |   0", a, b, carryin, carryout, sum);
	a = 1; b = 0; carryin = 1; #50
	$display("%b | %b | %b   | %b    | %b  |  0    |   1", a, b, carryin, carryout, sum);
	a = 1; b = 1; carryin = 0; #50
	$display("%b | %b | %b   | %b    | %b  |  0    |   1", a, b, carryin, carryout, sum);
	a = 1; b = 1; carryin = 1; #50
	$display("%b | %b | %b   | %b    | %b  |  1    |   1", a, b, carryin, carryout, sum);
	$finish();
    end

endmodule

adder.v
// Adder circuit

module behavioralFullAdder
(
    output sum, 
    output carryout,
    input a, 
    input b, 
    input carryin
);
    // Uses concatenation operator and built-in '+'
    assign {carryout, sum}=a+b+carryin;
endmodule

module structuralFullAdder
(
    output sum, 
    output carryout,
    input a, 
    input b, 
    input carryin
);
   
    wire c, d, e;
	xor ABxor(c, a, b);
	xor sumxor(sum, c, carryin);
	and carryand(d, c, carryin);
	and ABand(e, a, b);
	or carryoutor(carryout, d, e);

endmodule

<adder>.vcd
$date
	Wed Sep 25 00:20:56 2019
$end
$version
	Icarus Verilog
$end
$timescale
	1ps
$end
$scope module behavioralFullAdder $end
$var wire 1 ! a $end
$var wire 1 " b $end
$var wire 1 # carryin $end
$var wire 1 $ sum $end
$var wire 1 % carryout $end
$upscope $end
$scope module testFullAdder $end
$var wire 1 & sum $end
$var wire 1 ' carryout $end
$var reg 1 ( a $end
$var reg 1 ) b $end
$var reg 1 * carryin $end
$scope module adder $end
$var wire 1 ( a $end
$var wire 1 ) b $end
$var wire 1 + c $end
$var wire 1 * carryin $end
$var wire 1 ' carryout $end
$var wire 1 , d $end
$var wire 1 - e $end
$var wire 1 & sum $end
$upscope $end
$upscope $end
$enddefinitions $end
#0
$dumpvars
0-
0,
0+
0*
0)
0(
0'
0&
x%
x$
z#
z"
z!
$end
#50000
1&
1*
#100000
1+
0*
1)
#150000
1'
0&
1,
1*
#200000
0'
1&
0,
0*
0)
1(
#250000
1'
0&
1,
1*
#300000
0,
0+
1-
0*
1)
#350000
1&
1*
